outliers_101703296/remove_outliers.py
Outliers_101703296_thapar-1.0.1.dist-info/LICENSE.txt
Outliers_101703296_thapar-1.0.1.dist-info/METADATA
Outliers_101703296_thapar-1.0.1.dist-info/WHEEL
Outliers_101703296_thapar-1.0.1.dist-info/entry_points.txt
Outliers_101703296_thapar-1.0.1.dist-info/top_level.txt
Outliers_101703296_thapar-1.0.1.dist-info/RECORD
