Metadata-Version: 2.1
Name: Outliers-101703296-thapar
Version: 1.0.1
Summary: A row outlier removal Package Project of UCS633
Home-page: UNKNOWN
Author: Kuljot Singh Saggu
Author-email: kuljot2216@gmail.com
License: MIT
Platform: UNKNOWN
Classifier: Programming Language :: Python
Classifier: Operating System :: OS Independent
Classifier: License :: OSI Approved :: Python Software Foundation License
